{
    "Локомотив": [
        "Бакаев",
        "Баринов",
        "Батраков",
        "Веселов",
        "Воробьев",
        "Годяев",
        "Карпукас",
        "Комличенко",
        "Лантратов",
        "Мампасси",
        "Митрюшкин",
        "Монтес",
        "Морозов",
        "Мялковский",
        "Ненахов",
        "Ньямси",
        "Пиняев",
        "Погостнов",
        "Пруцев",
        "Рамирес",
        "Руденко",
        "Салтыков",
        "Сарвели",
        "Сильянов",
        "Тимофеев",
        "Топинка",
        "Фассон",
        "Шейко",
        "Щетинин"
    ],
    "Краснодар": [
        "Агкацев",
        "Батчи",
        "Голиков",
        "Гонсалес",
        "Гусейнов",
        "Дуглас",
        "Дэвид",
        "Жубал",
        "Карпов",
        "Кистенев",
        "Ковалевский",
        "Козлов",
        "Кокшаров",
        "Кордоба",
        "Корякин",
        "Коста",
        "Кривцов",
        "Кулаев",
        "Кучугура",
        "Ларионов",
        "Ленини",
        "Мацола",
        "Мукаилов",
        "Ндука",
        "Оласа",
        "Пальцев",
        "Перрен",
        "Петров",
        "Пивоваров",
        "Постриган",
        "Са",
        "Сантос",
        "Сафронов",
        "Сидоренко",
        "Сперцян",
        "Стежко",
        "Тормена",
        "Хмарин",
        "Черников"
    ],
    "Динамо": [
        "Александров",
        "Артур",
        "Бабаев",
        "Балахонов",
        "Бителло",
        "Боков",
        "Гагнидзе",
        "Гладышев",
        "Глебов",
        "Диас",
        "Зайдензаль",
        "Зайнутдинов",
        "Исаев",
        "Карраскаль",
        "Касерес",
        "Кудравец",
        "Купцов",
        "Кутицкий",
        "Лаксальт",
        "Лещук",
        "Лунев",
        "Майсторович",
        "Макаров",
        "Маричаль",
        "Маухуб",
        "Миранчук",
        "Мирошниченко",
        "Назаренко",
        "Нгамале",
        "Окишор",
        "Осипенко",
        "Расулов",
        "Сергеев",
        "Скопинцев",
        "Степанов",
        "Тюкавин",
        "Фернандес",
        "Фомин",
        "Чавес"
    ],
    "Рубин": [
        "Апшацев",
        "Арройо",
        "Безруков",
        "Вада",
        "Васильев",
        "Вуячич",
        "Грицаенко",
        "Даку",
        "Дрезгич",
        "Ежов",
        "Зотов",
        "Иванов",
        "Иву",
        "Йочич",
        "Кабутов",
        "Кузнецов",
        "Кузяев",
        "Лобов",
        "Ломовицкий",
        "Мальдонадо",
        "Мукба",
        "Нигматуллин",
        "Нижегородов",
        "Родин",
        "Рожков",
        "Сиве",
        "Ставер",
        "Тесленко",
        "Фаттахов",
        "Ходжа",
        "Чумич",
        "Чуни",
        "Шабанхаджай",
        "Швец",
        "Юкич"
    ],
    "ЦСКА": [
        "Абдулкадыров",
        "Айссауи",
        "Акинфеев",
        "Алвес",
        "Алеррандро",
        "Бандикян",
        "Баровский",
        "Бесаев",
        "Бондаренко",
        "Верде",
        "Виктор",
        "Виллиан",
        "Вильягра",
        "Гайич",
        "Глебов",
        "Данилов",
        "Дивеев",
        "Кармо",
        "Келвен",
        "Кисляк",
        "Койта",
        "Круговой",
        "Лукин",
        "Лусиано",
        "Лызлов",
        "Мойзес",
        "Мусаев",
        "Обляков",
        "Пономарчук",
        "Попович",
        "Пополитов",
        "Риванди",
        "Руис",
        "Рядно",
        "Савин",
        "Савинов",
        "Сериков",
        "Тороп",
        "Ушаков",
        "Файзуллаев",
        "Шуманский"
    ],
    "Балтика": [
        "Ангутаев",
        "Андраде",
        "Бевеев",
        "Бегун",
        "Беликов",
        "Бориско",
        "Варатынов",
        "Гасанбеков",
        "Гассама",
        "Горбачев",
        "Исик",
        "Йенне",
        "Камаев",
        "Ковалев",
        "Ковач",
        "Кукушкин",
        "Луна",
        "Любаков",
        "Макаров",
        "Манелов",
        "Мендель",
        "Мокин",
        "Мохаммад",
        "Мурид",
        "Никитин",
        "Обонин",
        "Оздоев",
        "Оффор",
        "Петров",
        "Пряхин",
        "Савицкий",
        "Саусь",
        "Степанов",
        "Стефанович",
        "Титков",
        "Уткин",
        "Фернандес",
        "Филин",
        "Хиль",
        "Чивич",
        "Эльдарушев"
    ],
    "Крылья Советов": [
        "Ахметов",
        "Бабкин",
        "Баняц",
        "Белтюков",
        "Бобер",
        "Божин",
        "Витюгов",
        "Гайч",
        "Гальдамес",
        "Грибакин",
        "Евгеньев",
        "Иванисеня",
        "Игнатенко",
        "Карпицкий",
        "Кокарев",
        "Лепский",
        "Лысов",
        "Ляхов",
        "Максимов",
        "Марин",
        "Недоспасов",
        "Олейников",
        "Ороз",
        "Першин",
        "Песьяков",
        "Печенин",
        "Попов",
        "Раков",
        "Рассказов",
        "Рахманович",
        "Соколов",
        "Сутормин",
        "Фернандо",
        "Фролов",
        "Хубулов",
        "Чернов",
        "Шитов"
    ],
    "Спартак": [
        "Бабич",
        "Барко",
        "Бонгонда",
        "Ву",
        "Гарсия",
        "Гузиев",
        "Денисов",
        "Джику",
        "Дмитриев",
        "Довбня",
        "Дуарте",
        "Заболотный",
        "Зобнин",
        "Зорин",
        "Лайкин",
        "Литвинов",
        "Максименко",
        "Мангаш",
        "Маркиньос",
        "Мартинс",
        "Массалыга",
        "Медина",
        "Мельник",
        "Пичиенко",
        "Помазун",
        "Пяткин",
        "Рощин",
        "Рябчук",
        "Самошников",
        "Солари",
        "Тихомиров",
        "Угальде",
        "Умяров",
        "Фернандеш",
        "Хлусевич",
        "Шитов"
    ],
    "Акрон": [
        "Агапов",
        "Базилевский",
        "Бакаев",
        "Бистрович",
        "Бокоев",
        "Болдырев",
        "Васютин",
        "Волков",
        "Галоян",
        "Гудиев",
        "Данилин",
        "Джаковац",
        "Джурасович",
        "Дзюба",
        "Димоски",
        "Дмитриев",
        "Кондаков",
        "Кузьменко",
        "Кузьмин",
        "Лончар",
        "Марадишвили",
        "Морозов",
        "Неделчару",
        "Пестряков",
        "Попенков",
        "Роча",
        "Савичев",
        "Севикян",
        "Соловьев",
        "Тавареш",
        "Тереховский",
        "Фернандес",
        "Хосонов",
        "Чалигава",
        "Чибота",
        "Шершов",
        "Эсанов",
        "Эшковал"
    ],
    "Пари НН": [
        "Александров",
        "Бедошвили",
        "Боженов",
        "Боселли",
        "Бреславцев",
        "Весино",
        "Генералов",
        "Грулев",
        "Ермаков",
        "Ивлев",
        "Каккоев",
        "Калинский",
        "Карапузов",
        "Карич",
        "Кастильо",
        "Коледин",
        "Кошкин",
        "Крашевский",
        "Лапинский",
        "Лесовой",
        "Лукьянов",
        "Майга",
        "Медведев",
        "Мелентьев",
        "Ожегович",
        "Олусегун",
        "Пигас",
        "Сарфо",
        "Сифас",
        "Смелов",
        "Тичич",
        "Трошечкин",
        "Турбо",
        "Фаринья",
        "Федоров",
        "Царукян",
        "Чистяков",
        "Шнапцев",
        "Эктов"
    ],
    "Зенит": [
        "Адамов",
        "Алип",
        "Барриос",
        "Булыгин",
        "Бязров",
        "Вега",
        "Вендел",
        "Вершинин",
        "Глушенков",
        "Гойло",
        "Гонду",
        "Горшков",
        "Дркушич",
        "Ерохин",
        "Жерсон",
        "Зделар",
        "Караваев",
        "Кассьерра",
        "Кержаков",
        "Латышонок",
        "Мантуан",
        "Михайлов",
        "Москвичев",
        "Мостовой",
        "Нино",
        "Педро",
        "Ренан",
        "Сантос",
        "Соболев",
        "Столбов",
        "Шилов",
        "Энрике",
        "Эракович"
    ],
    "Ростов": [
        "Аджаса",
        "Азнауров",
        "Амосов",
        "Андриянов",
        "Бабакин",
        "Байрамян",
        "Вахания",
        "Голенков",
        "Жбанов",
        "Зубенко",
        "Игнатов",
        "Калинин",
        "Колтаков",
        "Комаров",
        "Кучаев",
        "Лангович",
        "Мелехин",
        "Мельников",
        "Миронов",
        "Мохеби",
        "Мухин",
        "Одоевский",
        "Поярков",
        "Прохин",
        "Радченко",
        "Роналдо",
        "Рязанов",
        "Сако",
        "Саравия",
        "Семенчук",
        "Соловьев",
        "Сулейманов",
        "Тарасов",
        "Титов",
        "Тоневицкий",
        "Хаджикадунич",
        "Ханкич",
        "Чернов",
        "Чистяков",
        "Шамонин",
        "Шанталий",
        "Щетинин",
        "Эль-Аскалани",
        "Ятимов"
    ],
    "Ахмат": [
        "Бериша",
        "Богосавац",
        "Гаджиев",
        "Гадио",
        "Гаибов",
        "Гандри",
        "Диале",
        "Жемалетдинов",
        "Заре",
        "Ибишев",
        "Исмаэл",
        "Касинтура",
        "Келиану",
        "Конате",
        "Магомедов",
        "Мансилья",
        "Махрауи",
        "Мелкадзе",
        "Мосейчук",
        "Ндонг",
        "Садулаев",
        "Самородов",
        "Сидоров",
        "Талаль",
        "Тарамов",
        "Ташаев",
        "Тодорович",
        "Турищев",
        "Ульянов",
        "Уциев",
        "Шатара",
        "Шелия",
        "Якуев"
    ],
    "Оренбург": [
        "Барановский",
        "Болотов",
        "Бубанья",
        "Ведерников",
        "Горелов",
        "Гузина",
        "Гулько",
        "Гюрлюк",
        "Давыдов",
        "Жезус",
        "Зотов",
        "Игнатьев",
        "Камилов",
        "Касимов",
        "Квеквескири",
        "Кейрос",
        "Керин",
        "Косерик",
        "Ломакин",
        "Мартынов",
        "Минатулаев",
        "Муфи",
        "Овсянников",
        "Оганесян",
        "Поройков",
        "Ревазов",
        "Рыбчинский",
        "Савельев",
        "Сахархизан",
        "Скичко",
        "Столбов",
        "Сысуев",
        "Сыщенко",
        "Татаев",
        "Томпсон",
        "Тюленев",
        "Ходанович",
        "Хотулев",
        "Ценов",
        "Чичинадзе",
        "Шилов"
    ],
    "Динамо Махачкала": [
        "Агаларов",
        "Аззи",
        "Акаев",
        "Аларкон",
        "Алибеков",
        "Ахмедов",
        "Будунов",
        "Волк",
        "Гаджиев",
        "Глушков",
        "Джабраилов",
        "Джапо",
        "Зайнивов",
        "Зайнудинов",
        "Зинович",
        "Ибрагимов",
        "Кагермазов",
        "Карабашев",
        "Крачковский",
        "Магомедов",
        "Мастури",
        "Миро",
        "Мрезиг",
        "Мубарик",
        "Помешкин",
        "Сандрачук",
        "Сердеров",
        "Сундуков",
        "Табидзе",
        "Хоссейннежад",
        "Храмцов",
        "Шихалиев",
        "Шумахов"
    ],
    "Сочи": [
        "Аберден",
        "Агбалака",
        "Алвес",
        "Ангбан",
        "Аносов",
        "Аттийят-алла",
        "Балкизов",
        "Барт",
        "Бочаров",
        "Васильев",
        "Волков",
        "Гуарирапа",
        "Дегтев",
        "Дюпин",
        "Ежов",
        "Заболотный",
        "Заика",
        "Зиньковский",
        "Игнатов",
        "Кайнов",
        "Калинов",
        "Камано",
        "Киракосян",
        "Коваленко",
        "Кожемякин",
        "Корнеев",
        "Кравцов",
        "Крамарич",
        "Литвинов",
        "Ломаев",
        "Магаль",
        "Макарчук",
        "Мелешин",
        "Мециев",
        "Мухин",
        "Никитин",
        "Носатый",
        "Осипов",
        "Пасевич",
        "Рудаков",
        "Сааведра",
        "Солдатенков",
        "Стоич",
        "Стойисавлевич",
        "Суслов",
        "Терехов",
        "Тоцкий",
        "Федоров",
        "Чирков",
        "Шагиахметов"
    ]
}